{
  "appPageId" : "b84cf09c-49cf-4f20-9590-0a71da5b81b0",
  "componentName" : "siteforce:sldsOneColLayout",
  "id" : "a0773a85-38c8-4248-b27d-b45732f2a35e",
  "label" : "Report List",
  "regions" : [ {
    "id" : "e0ba81df-e5fa-44ae-88ac-8b926a7e944f",
    "regionName" : "header",
    "type" : "region"
  }, {
    "components" : [ {
      "componentAttributes" : { },
      "componentName" : "forceCommunity:reportList",
      "id" : "3908eb56-125b-4b99-9646-b93c330198ef",
      "renderPriority" : "NEUTRAL",
      "renditionMap" : { },
      "type" : "component"
    } ],
    "id" : "2cd6ab73-0754-44e6-9d56-2f396e6271c4",
    "regionName" : "content",
    "type" : "region"
  }, {
    "id" : "5df3729a-e60a-4873-9cb1-e95cc2ffb5d7",
    "regionName" : "footer",
    "type" : "region"
  } ],
  "themeLayoutType" : "Inner",
  "type" : "view",
  "viewType" : "list-00O"
}