{
  "appPageId" : "b84cf09c-49cf-4f20-9590-0a71da5b81b0",
  "componentName" : "siteforce:sldsOneColLayout",
  "id" : "8a73fa8d-28fd-4459-82bf-5f88b7ba5e01",
  "label" : "User Profile",
  "regions" : [ {
    "id" : "479088db-5a25-46b3-b4ae-ee1eeabae679",
    "regionName" : "header",
    "type" : "region"
  }, {
    "components" : [ {
      "componentAttributes" : {
        "caseCreateLabel" : "Create Case",
        "caseFilterName" : "AllOpenCases",
        "caseHeaderLabel" : "My Cases",
        "casesTabLabel" : "Cases",
        "detailsTabLabel" : "Details",
        "feedTabLabel" : "Feed",
        "knowledgeableAboutTitle" : "Knows About",
        "maxTopics" : 5,
        "recognitionbuttonLabel" : "Give",
        "relatedTabLabel" : "Related",
        "showAllUpdates" : false,
        "showBadges" : true,
        "showFullPhotoAsCircle" : true,
        "showKnowledgeableAbout" : true,
        "showRelatedList" : true,
        "showReputationInInfluenceCard" : false,
        "showStats" : true,
        "userBadgesTitle" : "Recognition Badges",
        "userId" : "{!recordId}",
        "userStatsTitle" : "Influence"
      },
      "componentName" : "forceCommunity:userRecordHome",
      "id" : "1d2f2eac-aa77-495e-a831-4a0859f6699d",
      "renderPriority" : "NEUTRAL",
      "renditionMap" : { },
      "type" : "component"
    } ],
    "id" : "81504235-ca33-475b-bb61-2c7193330a66",
    "regionName" : "content",
    "type" : "region"
  }, {
    "id" : "a7259394-ccd1-44ab-b1f5-3afb3e7be8ac",
    "regionName" : "footer",
    "type" : "region"
  } ],
  "themeLayoutType" : "Inner",
  "type" : "view",
  "viewType" : "detail-005"
}