{
  "appPageId" : "bf67aa00-1cf1-4a5c-8097-1d468d4e1829",
  "componentName" : "siteforce:sldsOneColLayout",
  "id" : "4946dbc6-cd44-4ef3-99bc-f4f598957648",
  "label" : "My Entitlements",
  "regions" : [ {
    "id" : "d6e4bf6d-3568-4936-98bf-065cb8942109",
    "regionName" : "header",
    "type" : "region"
  }, {
    "components" : [ {
      "componentAttributes" : { },
      "componentName" : "c:NCP_MyEntitlementsCmp",
      "id" : "05ef0e74-c87d-431b-814e-434f86e0f3a6",
      "renderPriority" : "NEUTRAL",
      "renditionMap" : { },
      "type" : "component"
    } ],
    "id" : "cabe39c0-9598-414c-b447-c1b5a40faf9a",
    "regionName" : "content",
    "type" : "region"
  }, {
    "components" : [ {
      "componentAttributes" : { },
      "componentName" : "c:NCP_GDPRCookieComponent",
      "id" : "522ea90e-6259-4d8a-8704-1728bfff639d",
      "renderPriority" : "NEUTRAL",
      "renditionMap" : { },
      "type" : "component"
    } ],
    "id" : "2cb3267f-a0f6-4205-ac85-350cc9e2f5eb",
    "regionName" : "footer",
    "type" : "region"
  }, {
    "components" : [ {
      "componentAttributes" : {
        "customHeadTags" : "",
        "description" : "",
        "title" : "My Entitlements"
      },
      "componentName" : "forceCommunity:seoAssistant",
      "id" : "db3bbb84-977b-4386-b4f4-abe9942ad3d7",
      "renditionMap" : { },
      "type" : "component"
    } ],
    "id" : "74624e64-6527-4658-8f03-257c84fa396a",
    "regionName" : "sfdcHiddenRegion",
    "type" : "region"
  } ],
  "themeLayoutType" : "Inner",
  "type" : "view",
  "viewType" : "custom-my-entitlements"
}