{
  "appPageId" : "e1a17645-2cc2-473d-958f-f0715a223047",
  "componentName" : "siteforce:sldsOneColLayout",
  "id" : "99e85309-de90-4d53-ae7e-9b76d9f1dc1f",
  "label" : "Flow",
  "regions" : [ {
    "id" : "7740d9d3-ed7a-469e-a8fa-b84f8db700cf",
    "regionName" : "header",
    "type" : "region"
  }, {
    "components" : [ {
      "componentAttributes" : {
        "flowArguments" : "",
        "flowLayout" : "oneColumn",
        "flowName" : "{!flowName}"
      },
      "componentName" : "forceCommunity:flowCommunity",
      "id" : "4a3dffdf-4226-4936-8a31-dacea8acf788",
      "renderPriority" : "NEUTRAL",
      "renditionMap" : { },
      "type" : "component"
    } ],
    "id" : "e66b8f3f-398f-48ff-8b78-537832c50ee5",
    "regionName" : "content",
    "type" : "region"
  }, {
    "id" : "78f4e5b7-9393-4ac4-90c8-dc33b877b2f1",
    "regionName" : "footer",
    "type" : "region"
  } ],
  "themeLayoutType" : "Inner",
  "type" : "view",
  "viewType" : "flow"
}