{
  "appPageId" : "3fe8c56d-7b29-44cc-9038-f4e27bc50371",
  "componentName" : "siteforce:sldsOneColLayout",
  "id" : "7d4d0704-cac0-47cb-87ec-68676e886b46",
  "label" : "Support Ticket Related List",
  "regions" : [ {
    "id" : "39593eb0-dee5-4fb4-8530-80c0ce63d8de",
    "regionName" : "header",
    "type" : "region"
  }, {
    "components" : [ {
      "componentAttributes" : {
        "parentRecordId" : "{!parentRecordId}",
        "relatedListName" : "{!relatedListName}"
      },
      "componentName" : "forceCommunity:relatedList",
      "id" : "14eea770-d7fc-48fd-89b3-accf8772fcdd",
      "renderPriority" : "NEUTRAL",
      "renditionMap" : { },
      "type" : "component"
    } ],
    "id" : "acbc534d-8937-49bb-9081-d75b40828828",
    "regionName" : "content",
    "type" : "region"
  }, {
    "id" : "be96bc36-5535-4134-9a2a-5ac25261f3a5",
    "regionName" : "footer",
    "type" : "region"
  } ],
  "themeLayoutType" : "Inner",
  "type" : "view",
  "viewType" : "relatedlist-500"
}