{
  "cart": {
    "cartSO": {
      "BusinessObjectType__c": "Proposal",
      "BusinessObjectId__c": "a1ki0000000GO4qAAG",
      "BaseRelationCount__c": 0,
      "OwnerId": "005i0000000atlMAAQ",
      "Proposald__c": "a1ki0000000GO4qAAG",
      "LastModifiedDate": 1432233593000,
      "LastActivityDate": 1429660800000,
      "AncestorId__c": "a0pi0000008HInBAAW",
      "SystemModstamp": 1432233593000,
      "PrimordialId__c": "a0pi0000008HInBAAW",
      "AccountId__r": {
        "Name": "Acme - Widgets",
        "Id": "001i0000008YMPrAAO"
      },
      "LastModifiedById": "005i0000000atlMAAQ",
      "IsTransient__c": true,
      "AccountId__c": "001i0000008YMPrAAO",
      "PriceListId__c": "a0ei0000000JatUAAS",
      "VersionNumber__c": 2,
      "IsPricePending__c": false,
      "Name": "Product Config - DDs Empty Cart2",
      "CreatedById": "005i0000000atlMAAQ",
      "CreatedDate": 1429728687000,
      "NumberOfItems__c": 14,
      "IsDeleted": false,
      "Id": "a0pi0000008HIqBAAW",
      "EffectivePriceListId__c": "a0ei0000000JatUAAS",
      "Status__c": "Saved",
      "Proposald__r": {
        "Name": "Q-00000852",
        "Apttus_Proposal__Opportunity__r": {
          "Name": "Acme - 1,200 Widgets",
          "Id": "006i0000003hvyWAAQ"
        },
        "RecordTypeId": "012i0000000bCnMAAU",
        "Id": "a1ki0000000GO4qAAG",
        "Apttus_Proposal__Opportunity__c": "006i0000003hvyWAAQ"
      },
      "SummaryGroupType__c": "Category"
    }
  },
  "timeTaken": 186
}
