{
  "appPageId" : "b84cf09c-49cf-4f20-9590-0a71da5b81b0",
  "componentName" : "siteforce:sldsOneColLayout",
  "id" : "11715de6-7437-480a-b153-ed6e20499028",
  "label" : "Create Record",
  "regions" : [ {
    "id" : "14dcd635-880e-4ae3-bb3e-7a760c042cb9",
    "regionName" : "header",
    "type" : "region"
  }, {
    "components" : [ {
      "componentAttributes" : {
        "actionApiName" : "{!actionApiName}"
      },
      "componentName" : "forceCommunity:createRecordForm",
      "id" : "6d9c628a-cff6-4fff-9ddb-20ba586610ef",
      "renderPriority" : "NEUTRAL",
      "renditionMap" : { },
      "type" : "component"
    } ],
    "id" : "cb79a922-af22-4c36-9b97-88271e02be4b",
    "regionName" : "content",
    "type" : "region"
  }, {
    "id" : "782c844c-b074-46cc-aca4-f189a0e4806c",
    "regionName" : "footer",
    "type" : "region"
  } ],
  "themeLayoutType" : "Inner",
  "type" : "view",
  "viewType" : "createrecord"
}