{
  "appPageId" : "9f4a6051-080b-4897-b430-b5887244e4b4",
  "componentName" : "siteforce:sldsOneColLayout",
  "id" : "ed181f09-b460-48ff-a031-827af02f3529",
  "label" : "Login Error",
  "regions" : [ {
    "id" : "fc682b4f-8b43-4675-bb16-68925325d066",
    "regionName" : "header",
    "type" : "region"
  }, {
    "components" : [ {
      "componentAttributes" : {
        "richTextValue" : "<div style=\"text-align: center;\">Invalid Page</div>"
      },
      "componentName" : "forceCommunity:richTextInline",
      "id" : "9f9edc2c-42bd-4ba8-a36c-1a6415161647",
      "renderPriority" : "NEUTRAL",
      "renditionMap" : { },
      "type" : "component"
    } ],
    "id" : "e9bc59b5-716c-441e-ae15-dfce4b4c01ff",
    "regionName" : "content",
    "type" : "region"
  }, {
    "id" : "ef16b1fb-526b-4b97-b129-6b738be938f2",
    "regionName" : "footer",
    "type" : "region"
  }, {
    "components" : [ {
      "componentAttributes" : {
        "customHeadTags" : "",
        "description" : "",
        "title" : "Login Error"
      },
      "componentName" : "forceCommunity:seoAssistant",
      "id" : "75e01092-07dd-4c8a-a7c9-a631bc59f180",
      "renditionMap" : { },
      "type" : "component"
    } ],
    "id" : "22e534b2-4840-402d-990f-69866a733892",
    "regionName" : "sfdcHiddenRegion",
    "type" : "region"
  } ],
  "themeLayoutType" : "Login",
  "type" : "view",
  "viewType" : "login-error"
}